[
  {
    "date": "2025-11-20",
    "displayDate": "Nov 20",
    "title": "Company Registered",
    "description": "Trinity Technology Pvt. Ltd. registered with the Office of the Company Registrar (OCR), Nepal.",
    "category": "Registration",
    "showOnAbout": true
  },
  {
    "date": "2026-02-14",
    "displayDate": "Feb 14",
    "title": "Capture the Flag (CTF) Event",
    "description": "Organized a cybersecurity CTF event for local students and professionals.",
    "category": "Event",
    "galleryImagePrefix": "2026-02-14_ctf",
    "showOnAbout": false
  },
  {
    "date": "2026-02-19",
    "displayDate": "Feb 19-21",
    "title": "U.S. Startup Weekend Challenge",
    "description": "3-day intensive startup sprint.",
    "galleryImagePrefix": "2026-02-19_startup_challenge",
    "category": "Event",
    "showOnAbout": true
  },
  {
    "date": "2026-02-25",
    "displayDate": "Feb 25",
    "title": "Cybersecurity Awareness Training",
    "description": "Conducted for 3 different schools.",
    "galleryImagePrefix": "2026-02-24_cybersecurity_awareness",
    "category": "Community",
    "showOnAbout": false
  },
  {
    "date": "2026-03-21",
    "displayDate": "Mar 21",
    "title": "OWASP Kathmandu Meetup - 0x08",
    "description": "Sponsored and participated.",
    "category": "Achievement",
    "galleryImagePrefix": "2026-03-21_owasp_ktm_0x08",
    "showOnAbout": true
  },
  {
    "date": "2026-05-09",
    "displayDate": "May 9",
    "title": "[UPCOMING] Live Hacking Session",
    "description": "Join us for an interactive live hacking session where we demonstrate real-world attack techniques.",
    "category": "Event",
    "showOnAbout": true
  }
]
